pdm_click-0.1.4.dist-info/METADATA
pdm_click-0.1.4.dist-info/WHEEL
pdm_click-0.1.4.dist-info/entry_points.txt
pdm_click/__init__.py
pdm_click/build_hooks.py
pdm_click-0.1.4.dist-info/RECORD
